jira_notifications/__init__.py
jira_notifications/helper.py
jira_notifications/jira_client.py
jira_notifications/logger.py
jira_notifications/main.py
jira_notifications/toast.py
jira_notifications/triggers.py
jira_notifications/assets/jira.png
jira_notifications/assets/jira.wav
jira_notifications-1.0.4.dist-info/LICENSE.txt
jira_notifications-1.0.4.dist-info/METADATA
jira_notifications-1.0.4.dist-info/WHEEL
jira_notifications-1.0.4.dist-info/entry_points.txt
jira_notifications-1.0.4.dist-info/top_level.txt
jira_notifications-1.0.4.dist-info/RECORD
