Metadata-Version: 2.1
Name: jira-notifications
Version: 1.0.4
Summary: Add a short description here!
Home-page: https://github.com/gruppferi/jira-notifications.git
Author: Ferdows Shahryar
Author-email: s.ferdows@hotmail.com
License: MIT
Platform: any
Classifier: Development Status :: 4 - Beta
Classifier: Programming Language :: Python
License-File: LICENSE.txt
Requires-Dist: jira >=3.6.0
Requires-Dist: pytest >=8.0.0
Requires-Dist: PyYAML >=6.0.1
Requires-Dist: notify2 >=0.3.1
Requires-Dist: importlib-metadata ; python_version < "3.8"
Provides-Extra: testing
Requires-Dist: setuptools ; extra == 'testing'
Requires-Dist: pytest ; extra == 'testing'
Requires-Dist: pytest-cov ; extra == 'testing'
